dumas/__about__.py
dumas/__init__.py
dumas/__main__.py
dumas/cli/__init__.py
dumas/lib/__init__.py
dumas/lib/interpreters.py
dumas/lib/renderer.py
dumas-0.0.6.dist-info/METADATA
dumas-0.0.6.dist-info/WHEEL
dumas-0.0.6.dist-info/entry_points.txt
dumas-0.0.6.dist-info/licenses/LICENSE.txt
dumas-0.0.6.dist-info/RECORD
