Metadata-Version: 2.3
Name: dumas
Version: 0.0.6
Project-URL: Documentation, https://github.com/aleivag/dumas#readme
Project-URL: Issues, https://github.com/aleivag/dumas/issues
Project-URL: Source, https://github.com/aleivag/dumas
Author-email: Alvaro Leiva Geisse <aleivag@gmail.com>
License-Expression: MIT
License-File: LICENSE.txt
Classifier: Development Status :: 4 - Beta
Classifier: Programming Language :: Python
Classifier: Programming Language :: Python :: 3.10
Classifier: Programming Language :: Python :: 3.11
Classifier: Programming Language :: Python :: 3.12
Classifier: Programming Language :: Python :: Implementation :: CPython
Classifier: Programming Language :: Python :: Implementation :: PyPy
Requires-Python: >=3.10
Requires-Dist: black
Requires-Dist: click
Requires-Dist: ipython
Requires-Dist: libcst
Requires-Dist: marko
Requires-Dist: pydantic
